Digital VLSI design - Logic Implementation and Layout Design, Verilog based Design/Verilog/serial_adder.v
module serial_adder(
    input clock,
    input [7:0] DA,
    input [7:0] DB,
    input Cin1,
    output Cout,
    output reg [7:0] Sum,
    input load
    ); 

 
    reg Cin; 
    wire S;
    wire Cout; 
    reg [7:0] A, B;
    wire w1, w2, w3; 

    // 1 Bit Adder - Gate Level Modelling
    xor (w1, A[0], B[0]);
    and (w2, w1, Cin); 
    and (w3, A[0], B[0]);
    xor (S, w1, Cin);
    or (Cout, w2, w3);

   initial $monitor("time=%d, A=%d, B=%d, load=%b, Cin=%b, A[0]=%b, B[0]=%b, Cout=%b, Sum=%b", $time, A, B, load, Cin, A[0], B[0], Cout, Sum);

    always @( posedge clock, posedge load) 
    begin
        if(load==0) 
        begin 
            A[0]<=A[1];
            A[1]<=A[2];
            A[2]<=A[3];
            A[3]<=A[4];
            A[4]<=A[5];
            A[5]<=A[6];
            A[6]<=A[7]; 
            A[7]<=A[0];

            B[0]<=B[1];
            B[1]<=B[2];
            B[2]<=B[3];
            B[3]<=B[4];
            B[4]<=B[5];
            B[5]<=B[6];
            B[6]<=B[7];
            B[7]<=B[0];
            Cin<=Cout; 

            Sum[0]<=Sum[1];
            Sum[1]<=Sum[2];
            Sum[2]<=Sum[3];
            Sum[3]<=Sum[4];
            Sum[4]<=Sum[5];
            Sum[5]<=Sum[6];
            Sum[6]<=Sum[7];
            Sum[7]<=S;
        end 

        if(load==1)
        begin 
            A<=DA;
            B<=DB;
            Cin<=Cin1;
        end
    end
endmodule

Digital VLSI design - Logic Implementation and Layout Design, Verilog based Design/Verilog/testbench.v
`timescale 1ns/10ps
`include "serial_adder.v"
module serial_adder_tb;
    reg [7:0] A,B;
    wire Cout;
    reg Cin;
    reg clock; 
    wire [7:0] Sum;
    reg load;
    serial_adder SA(
        .clock(clock),
        .DA(A),
        .DB(B),
        .Cin1(Cin),
        .Cout(Cout),
        .load(load),
        .Sum(Sum)
        );

    initial
    begin
        $dumpfile("serial_adder.vcd");
        $dumpvars(0, serial_adder_tb);
        #5 A = 8'b00001010; B = 8'b00001111; Cin = 0; load = 1;
        #5 load = 0;
        clock=1'b1;
        forever #5 clock=~clock;
    end
           initial #90
            $finish;

endmodule

Digital VLSI design - Logic Implementation and Layout Design, Verilog based Design/Verilog/serial_adder.vcd
$date
	Mon Aug 02 19:58:34 2021
$end
$version
	Icarus Verilog
$end
$timescale
	10ps
$end
$scope module serial_adder_tb $end
$var wire 8 ! Sum [7:0] $end
$var wire 1 " Cout $end
$var reg 8 # A [7:0] $end
$var reg 8 $ B [7:0] $end
$var reg 1 % Cin $end
$var reg 1 & clock $end
$var reg 1 ' load $end
$scope module SA $end
$var wire 1 % Cin1 $end
$var wire 1 " Cout $end
$var wire 8 ( DA [7:0] $end
$var wire 8 ) DB [7:0] $end
$var wire 1 * S $end
$var wire 1 & clock $end
$var wire 1 ' load $end
$var wire 1 + w1 $end
$var wire 1 , w2 $end
$var wire 1 - w3 $end
$var reg 8 . A [7:0] $end
$var reg 8 / B [7:0] $end
$var reg 1 0 Cin $end
$var reg 8 1 Sum [7:0] $end
$upscope $end
$upscope $end
$enddefinitions $end
#0
$dumpvars
bx 1
x0
bx /
bx .
x-
x,
x+
x*
bx )
bx (
x'
x&
x%
bx $
bx #
x"
bx !
$end
#500
1*
0"
1+
0-
0,
00
b1111 /
b1010 .
1'
0%
b1111 $
b1111 )
b1010 #
b1010 (
#1000
0*
1"
0+
1-
b1xxxxxxx !
b1xxxxxxx 1
b10000111 /
b101 .
1&
0'
#1500
0&
#2000
1,
1"
1+
0-
0*
b1xxxxxx !
b1xxxxxx 1
10
b11000011 /
b10000010 .
1&
#2500
0&
#3000
0,
1*
0+
1-
b1xxxxx !
b1xxxxx 1
b11100001 /
b1000001 .
1&
#3500
0&
#4000
0"
0-
b1001xxxx !
b1001xxxx 1
b11110000 /
b10100000 .
1&
#4500
0&
#5000
0*
b11001xxx !
b11001xxx 1
00
b1111000 /
b1010000 .
1&
#5500
0&
#6000
b11001xx !
b11001xx 1
b111100 /
b101000 .
1&
#6500
0&
#7000
b11001x !
b11001x 1
b11110 /
b10100 .
1&
#7500
0&
#8000
1*
1+
b11001 !
b11001 1
b1111 /
b1010 .
1&
#8500
0&
#9000
0*
1"
0+
1-
b10001100 !
b10001100 1
b10000111 /
b101 .
1&
